Metadata-Version: 2.4
Name: Gixy-Next
Version: 0.1.2
Summary: Open source NGINX configuration security scanner for detecting nginx security/performance misconfigurations
Home-page: https://gixy.io/
Author: Joshua Rogers
Author-email: gixy@joshua.hu
License: MPL-2.0
Project-URL: Homepage, https://gixy.io/
Project-URL: Documentation, https://gixy.io/
Project-URL: Source, https://github.com/MegaManSec/gixy-next
Project-URL: Issue Tracker, https://github.com/MegaManSec/gixy-next/issues
Project-URL: Original Gixy, https://github.com/yandex/gixy
Keywords: nginx,nginx security,nginx hardening,nginx configuration,nginx config,nginx config scanner,nginx configuration checker,nginx config linter,nginx security scanner,nginx configuration static analyzer,nginx vulnerability scanner,nginx.conf security audit,configuration compliance,configuration security,static analysis,ssrf,http response splitting,host header spoofing,version disclosure,redos,gixy,gixy next,gixy-ng,gixyng
Classifier: Environment :: Console
Classifier: Intended Audience :: System Administrators
Classifier: Intended Audience :: Developers
Classifier: Intended Audience :: Information Technology
Classifier: Topic :: Security
Classifier: Topic :: System :: Systems Administration
Classifier: Topic :: Internet :: WWW/HTTP :: Site Management
Classifier: Topic :: Software Development :: Quality Assurance
Classifier: Topic :: Software Development :: Testing
Classifier: Topic :: Utilities
Classifier: Operating System :: POSIX :: Linux
Classifier: Programming Language :: Python
Classifier: Programming Language :: Python :: 3
Classifier: Programming Language :: Python :: 3.6
Classifier: Programming Language :: Python :: 3.7
Classifier: Programming Language :: Python :: 3.8
Classifier: Programming Language :: Python :: 3.9
Classifier: Programming Language :: Python :: 3.10
Classifier: Programming Language :: Python :: 3.11
Classifier: Programming Language :: Python :: 3.12
Classifier: Programming Language :: Python :: 3.14
Classifier: Programming Language :: Python :: 3.15
Requires-Python: >=3.6
License-File: LICENSE
Requires-Dist: crossplane>=0.5.8
Requires-Dist: cached-property>=1.2.0; python_version < "3.8"
Requires-Dist: argparse>=1.4.0; python_version < "3.2"
Requires-Dist: Jinja2>=2.8
Requires-Dist: ConfigArgParse>=0.11.0
Requires-Dist: tldextract==3.1.2; python_version >= "3.6" and python_version < "3.7"
Requires-Dist: tldextract==4.0.0; python_version >= "3.7" and python_version < "3.8"
Requires-Dist: tldextract<5.3.0,>=5.1.2; python_version >= "3.8" and python_version < "3.9"
Requires-Dist: tldextract>=5.3.0; python_version >= "3.9"
Provides-Extra: tests
Requires-Dist: pytest>=7.0.0; extra == "tests"
Requires-Dist: pytest-xdist; extra == "tests"
Provides-Extra: dev
Requires-Dist: pytest>=7.0.0; extra == "dev"
Requires-Dist: pytest-xdist; extra == "dev"
Requires-Dist: coverage>=4.3; extra == "dev"
Requires-Dist: flake8>=3.2; extra == "dev"
Requires-Dist: tox>=2.7.0; extra == "dev"
Requires-Dist: setuptools; extra == "dev"
Requires-Dist: twine; extra == "dev"
Provides-Extra: redos
Requires-Dist: requests>=2.20.0; extra == "redos"
Dynamic: author
Dynamic: author-email
Dynamic: classifier
Dynamic: description
Dynamic: description-content-type
Dynamic: home-page
Dynamic: keywords
Dynamic: license
Dynamic: license-file
Dynamic: project-url
Dynamic: provides-extra
Dynamic: requires-dist
Dynamic: requires-python
Dynamic: summary
